setup.py
tvdb_rest.egg-info/PKG-INFO
tvdb_rest.egg-info/SOURCES.txt
tvdb_rest.egg-info/dependency_links.txt
tvdb_rest.egg-info/not-zip-safe
tvdb_rest.egg-info/top_level.txt
tvdbrest/__init__.py
tvdbrest/client.py
tvdbrest/objects.py