Metadata-Version: 1.1
Name: tvdb-rest
Version: 0.1
Summary: Python client implementation for The TVDB REST API
Home-page: https://code.not-your-server.de/tvdb-rest.git
Author: Johann Schmitz
Author-email: johann@j-schmitz.net
License: GPL-3
Download-URL: https://code.not-your-server.de/tvdb-rest.git/tags/0.1.tar.gz
Platform: UNKNOWN
